<!DOCTYPE suite SYSTEM "http://testng.org/testng-1.0.dtd" >
<suite name="TestSuite">
    <parameter name="context" value="https://relengxl.psteering.com/PepsicoCorp_192_308651/"/>
    <parameter name="visible" value="true"/>


    <test name="AutoQA">
        <parameter name="rootTag" value="rootTag"/>


        <classes>
            <class name="tests.configuration.tags.SetTagList">
                <methods>


                </methods>
            </class>
        </classes>

    </test>
</suite>